pyloadanimate/__init__.py
pyloadanimate/load_animation.py
pyloadinganimate/__init__.py
pyloadinganimate/loadanimation.py
tests/__init__.py
tests/test_loadanimation.py
pyloadanimate-0.1.2.dist-info/METADATA
pyloadanimate-0.1.2.dist-info/WHEEL
pyloadanimate-0.1.2.dist-info/top_level.txt
pyloadanimate-0.1.2.dist-info/RECORD
