Metadata-Version: 2.1
Name: pyloadanimate
Version: 0.1.2
Summary: My first Python library
Author: Nakul S Kulkarni
License: MIT
Requires-Python: >=3.7
